remotecv_redis/__init__.py
remotecv_redis/loader.py
remotecv_redis-0.2.3.dist-info/LICENSE
remotecv_redis-0.2.3.dist-info/METADATA
remotecv_redis-0.2.3.dist-info/WHEEL
remotecv_redis-0.2.3.dist-info/top_level.txt
remotecv_redis-0.2.3.dist-info/RECORD
