Metadata-Version: 2.1
Name: remotecv-redis
Version: 0.2.3
Summary: Redis image loader for remotecv
Home-page: https://github.com/benneic/remotecv_redis
Author: Benn Eichhorn
Author-email: beichhor@gmail.com
License: MIT
Keywords: imaging face detection feature opencv redis thumbor storage loader
Platform: UNKNOWN
Classifier: Development Status :: 4 - Beta
Classifier: Intended Audience :: Developers
Classifier: License :: OSI Approved :: MIT License
Classifier: Natural Language :: English
Classifier: Operating System :: MacOS
Classifier: Operating System :: POSIX :: Linux
Classifier: Programming Language :: Python :: 2.6
Classifier: Topic :: Internet :: WWW/HTTP :: Dynamic Content
Classifier: Topic :: Multimedia :: Graphics :: Presentation
Requires-Dist: redis (<3.0.0,>=2.10.0)
